anges/__init__.py
anges/cli.py
anges/config.py
anges/agents/__init__.py
anges/agents/default_agent.py
anges/agents/orchestrator.py
anges/agents/task_analyzer.py
anges/agents/task_executor.py
anges/agents/agent_utils/__init__.py
anges/agents/agent_utils/agent_actions.py
anges/agents/agent_utils/agent_factory.py
anges/agents/agent_utils/base_agent.py
anges/agents/agent_utils/event_methods.py
anges/agents/agent_utils/events.py
anges/agents/agent_utils/mcp_actions.py
anges/agents/agent_utils/mime_files_reader.py
anges/cli_interface/__init__.py
anges/cli_interface/cli_runner.py
anges/configs/default_config.yaml
anges/prompt_templates/__init__.py
anges/prompt_templates/common_prompts.py
anges/prompt_templates/orchestrator_prompts.py
anges/prompt_templates/panel_discussion.py
anges/prompt_templates/task_analyzer_prompts.py
anges/utils/__init__.py
anges/utils/agent_call_agent.py
anges/utils/agent_common.py
anges/utils/agent_edit_file.py
anges/utils/data_handler.py
anges/utils/event_storage_service.py
anges/utils/inference_api.py
anges/utils/load_configs.py
anges/utils/mcp_manager.py
anges/utils/panel_discussion.py
anges/utils/parse_response.py
anges/utils/shared_base.py
anges/utils/shell_wrapper.py
anges/web_interface/__init__.py
anges/web_interface/agent_runner.py
anges/web_interface/event_storage.py
anges/web_interface/run_web_interface.py
anges/web_interface/web_interface.py
anges/web_interface/static/eslint.config.js
anges/web_interface/static/favicon.ico
anges/web_interface/static/package-lock.json
anges/web_interface/static/package.json
anges/web_interface/static/style.css
anges/web_interface/static/css/chat.css
anges/web_interface/static/js/SettingsPanel.js
anges/web_interface/static/js/chat.js
anges/web_interface/static/js/chatComponents.js
anges/web_interface/static/js/chatCore.js
anges/web_interface/static/js/chatDrawer.js
anges/web_interface/static/js/chatHistory.js
anges/web_interface/static/js/chatIndentation.js
anges/web_interface/static/js/inputForm.js
anges-0.1.1.dist-info/licenses/LICENSE
anges-0.1.1.dist-info/METADATA
anges-0.1.1.dist-info/WHEEL
anges-0.1.1.dist-info/entry_points.txt
anges-0.1.1.dist-info/top_level.txt
anges-0.1.1.dist-info/RECORD
