Metadata-Version: 2.4
Name: anges
Version: 0.1.1
Summary: Anges - An LLM Powered Engineering Agent System
Home-page: https://github.com/anges-ai/anges
Author: Anges Team
Author-email: me@anges.ai
Project-URL: Documentation, https://github.com/anges-ai/anges/tree/main/docs
Project-URL: Examples, https://github.com/anges-ai/anges/tree/main/examples
Project-URL: Source, https://github.com/anges-ai/anges
Project-URL: Bug Tracker, https://github.com/anges-ai/anges/issues
Keywords: ai,agent,orchestration,automation,framework,llm,openai,anthropic,google,vertexai,workflow,event-driven,multi-agent,assistant,custom-actions,plugin-system,ai-automation
Classifier: Development Status :: 3 - Alpha
Classifier: Intended Audience :: Developers
Classifier: Intended Audience :: Science/Research
Classifier: License :: OSI Approved :: MIT License
Classifier: Operating System :: OS Independent
Classifier: Programming Language :: Python :: 3
Classifier: Programming Language :: Python :: 3.8
Classifier: Programming Language :: Python :: 3.9
Classifier: Programming Language :: Python :: 3.10
Classifier: Programming Language :: Python :: 3.11
Classifier: Programming Language :: Python :: 3.12
Classifier: Programming Language :: Python :: 3.13
Classifier: Topic :: Software Development :: Libraries :: Python Modules
Classifier: Topic :: Scientific/Engineering :: Artificial Intelligence
Classifier: Topic :: Software Development :: Libraries :: Application Frameworks
Classifier: Topic :: System :: Distributed Computing
Classifier: Topic :: Internet :: WWW/HTTP :: Dynamic Content
Classifier: Framework :: Flask
Requires-Python: >=3.8
License-File: LICENSE
Requires-Dist: flask>=2.0.0
Requires-Dist: flask-cors>=3.0.0
Requires-Dist: flask-login>=0.6.0
Requires-Dist: requests>=2.25.0
Requires-Dist: python-dotenv>=0.19.0
Requires-Dist: openai>=1.0.0
Requires-Dist: vertexai>=1.0.0
Requires-Dist: anthropic>=0.3.0
Requires-Dist: panel>=1.0.0
Requires-Dist: google-generativeai>=0.3.0
Requires-Dist: pandas>=1.3.0
Requires-Dist: datasets>=2.0.0
Requires-Dist: pytest>=6.0.0
Requires-Dist: mime-files-reader>=0.2.0
Provides-Extra: dev
Requires-Dist: pytest>=6.0.0; extra == "dev"
Requires-Dist: pytest-cov>=2.12.0; extra == "dev"
Requires-Dist: black>=21.0.0; extra == "dev"
Requires-Dist: flake8>=3.9.0; extra == "dev"
Requires-Dist: mypy>=0.910; extra == "dev"
Provides-Extra: docs
Requires-Dist: sphinx>=4.0.0; extra == "docs"
Requires-Dist: sphinx-rtd-theme>=1.0.0; extra == "docs"
Requires-Dist: myst-parser>=0.15.0; extra == "docs"
Dynamic: author
Dynamic: author-email
Dynamic: classifier
Dynamic: description
Dynamic: description-content-type
Dynamic: home-page
Dynamic: keywords
Dynamic: license-file
Dynamic: project-url
Dynamic: provides-extra
Dynamic: requires-dist
Dynamic: requires-python
Dynamic: summary
